Workbook

Sheet Assumptions
A1: Assumptions
A2: Yellow cells with blue text are inputs. Casa updates C5 each morning from Lunch Money.
A4: Assumption | C4: Value | D4: Notes
A5: Exchange rate: primary-currency units per 1 unit of the second currency | C5: 0.86 | D5: e.g. EUR per USD. Every second-currency line converts with this.
A6: Management fee | C6: 0.1 | D6: Used by Income rows whose Deduction says "fee".
A7: Second currency | C7: USD | D7: The code in the Currency column that converts with C5.

Sheet Income
A1: Income (monthly)
A2: Gross per month. Deduction is a fraction (0.25) or the word fee (Assumptions C6).
A4: Source | B4: Currency | C4: Gross / month | D4: Deduction | E4: Net / month | F4: Net primary / month | G4: Notes
A5: Salary (Sam) | B5: USD | C5: 7000 | D5: 0.25 | E5: =IF(A5="","",C5*(1-IF(ISTEXT(D5),Assumptions!$C$6,N(D5)))) | F5: =IF(A5="",0,E5*IF(B5=Assumptions!$C$7,Assumptions!$C$5,1)) | G5: After US tax withholding
A6: Freelance (Alex) | B6: EUR | C6: 400 | D6: 0 | E6: =IF(A6="","",C6*(1-IF(ISTEXT(D6),Assumptions!$C$6,N(D6)))) | F6: =IF(A6="",0,E6*IF(B6=Assumptions!$C$7,Assumptions!$C$5,1))
E7: =IF(A7="","",C7*(1-IF(ISTEXT(D7),Assumptions!$C$6,N(D7)))) | F7: =IF(A7="",0,E7*IF(B7=Assumptions!$C$7,Assumptions!$C$5,1))
E8: =IF(A8="","",C8*(1-IF(ISTEXT(D8),Assumptions!$C$6,N(D8)))) | F8: =IF(A8="",0,E8*IF(B8=Assumptions!$C$7,Assumptions!$C$5,1))
E9: =IF(A9="","",C9*(1-IF(ISTEXT(D9),Assumptions!$C$6,N(D9)))) | F9: =IF(A9="",0,E9*IF(B9=Assumptions!$C$7,Assumptions!$C$5,1))
E10: =IF(A10="","",C10*(1-IF(ISTEXT(D10),Assumptions!$C$6,N(D10)))) | F10: =IF(A10="",0,E10*IF(B10=Assumptions!$C$7,Assumptions!$C$5,1))
E11: =IF(A11="","",C11*(1-IF(ISTEXT(D11),Assumptions!$C$6,N(D11)))) | F11: =IF(A11="",0,E11*IF(B11=Assumptions!$C$7,Assumptions!$C$5,1))
E12: =IF(A12="","",C12*(1-IF(ISTEXT(D12),Assumptions!$C$6,N(D12)))) | F12: =IF(A12="",0,E12*IF(B12=Assumptions!$C$7,Assumptions!$C$5,1))
E13: =IF(A13="","",C13*(1-IF(ISTEXT(D13),Assumptions!$C$6,N(D13)))) | F13: =IF(A13="",0,E13*IF(B13=Assumptions!$C$7,Assumptions!$C$5,1))
E14: =IF(A14="","",C14*(1-IF(ISTEXT(D14),Assumptions!$C$6,N(D14)))) | F14: =IF(A14="",0,E14*IF(B14=Assumptions!$C$7,Assumptions!$C$5,1))
E15: =IF(A15="","",C15*(1-IF(ISTEXT(D15),Assumptions!$C$6,N(D15)))) | F15: =IF(A15="",0,E15*IF(B15=Assumptions!$C$7,Assumptions!$C$5,1))
E16: =IF(A16="","",C16*(1-IF(ISTEXT(D16),Assumptions!$C$6,N(D16)))) | F16: =IF(A16="",0,E16*IF(B16=Assumptions!$C$7,Assumptions!$C$5,1))
E17: =IF(A17="","",C17*(1-IF(ISTEXT(D17),Assumptions!$C$6,N(D17)))) | F17: =IF(A17="",0,E17*IF(B17=Assumptions!$C$7,Assumptions!$C$5,1))
E18: =IF(A18="","",C18*(1-IF(ISTEXT(D18),Assumptions!$C$6,N(D18)))) | F18: =IF(A18="",0,E18*IF(B18=Assumptions!$C$7,Assumptions!$C$5,1))
... E20: =IF(A20="","",C20*(1-IF(ISTEXT(D20),Assumptions!$C$6,N(D20)))) | F20: =IF(A20="",0,E20*IF(B20=Assumptions!$C$7,Assumptions!$C$5,1))
A22: Total | F22: =SUM(F5:F20)

Sheet Expenses
A1: Expenses: the master list
A2: One row per expense. Monthly lines are fixed or daily (see category_map.yaml); Annual lines land in their due month; 5-Year lines are smoothed over 60 months.
A4: Category | B4: Item | C4: Currency | D4: Amount | E4: Frequency | F4: Due month (1–12) | G4: Monthly primary equiv. | H4: Annual primary | I4: Notes
A5: Housing | B5: Rent | C5: EUR | D5: 1600 | E5: Monthly | G5: =IF(B5="",0,D5*IF(C5=Assumptions!$C$7,Assumptions!$C$5,1)/IF(E5="Monthly",1,IF(E5="Annual",12,60))) | H5: =G5*12 | I5: Paid around the 25th for the next month
A6: Utilities | B6: Electricity | C6: EUR | D6: 90 | E6: Monthly | G6: =IF(B6="",0,D6*IF(C6=Assumptions!$C$7,Assumptions!$C$5,1)/IF(E6="Monthly",1,IF(E6="Annual",12,60))) | H6: =G6*12
A7: Utilities | B7: Internet and phones | C7: EUR | D7: 45 | E7: Monthly | G7: =IF(B7="",0,D7*IF(C7=Assumptions!$C$7,Assumptions!$C$5,1)/IF(E7="Monthly",1,IF(E7="Annual",12,60))) | H7: =G7*12
A8: Food | B8: Groceries | C8: EUR | D8: 700 | E8: Monthly | G8: =IF(B8="",0,D8*IF(C8=Assumptions!$C$7,Assumptions!$C$5,1)/IF(E8="Monthly",1,IF(E8="Annual",12,60))) | H8: =G8*12
A9: Food | B9: Restaurants | C9: EUR | D9: 250 | E9: Monthly | G9: =IF(B9="",0,D9*IF(C9=Assumptions!$C$7,Assumptions!$C$5,1)/IF(E9="Monthly",1,IF(E9="Annual",12,60))) | H9: =G9*12
A10: Childcare | B10: Nanny | C10: EUR | D10: 780 | E10: Monthly | G10: =IF(B10="",0,D10*IF(C10=Assumptions!$C$7,Assumptions!$C$5,1)/IF(E10="Monthly",1,IF(E10="Annual",12,60))) | H10: =G10*12 | I10: 180 every Friday in cash (52 × 180 ÷ 12)
A11: Childcare | B11: Swimming lessons | C11: EUR | D11: 60 | E11: Monthly | G11: =IF(B11="",0,D11*IF(C11=Assumptions!$C$7,Assumptions!$C$5,1)/IF(E11="Monthly",1,IF(E11="Annual",12,60))) | H11: =G11*12
A12: Transport | B12: Transit and taxis | C12: EUR | D12: 120 | E12: Monthly | G12: =IF(B12="",0,D12*IF(C12=Assumptions!$C$7,Assumptions!$C$5,1)/IF(E12="Monthly",1,IF(E12="Annual",12,60))) | H12: =G12*12
A13: Personal | B13: Clothes and haircuts | C13: EUR | D13: 150 | E13: Monthly | G13: =IF(B13="",0,D13*IF(C13=Assumptions!$C$7,Assumptions!$C$5,1)/IF(E13="Monthly",1,IF(E13="Annual",12,60))) | H13: =G13*12
A14: Lifestyle | B14: Subscriptions and outings | C14: EUR | D14: 120 | E14: Monthly | G14: =IF(B14="",0,D14*IF(C14=Assumptions!$C$7,Assumptions!$C$5,1)/IF(E14="Monthly",1,IF(E14="Annual",12,60))) | H14: =G14*12
A15: Household | B15: Household supplies | C15: EUR | D15: 150 | E15: Monthly | G15: =IF(B15="",0,D15*IF(C15=Assumptions!$C$7,Assumptions!$C$5,1)/IF(E15="Monthly",1,IF(E15="Annual",12,60))) | H15: =G15*12
A16: Health | B16: Health insurance | C16: USD | D16: 320 | E16: Monthly | G16: =IF(B16="",0,D16*IF(C16=Assumptions!$C$7,Assumptions!$C$5,1)/IF(E16="Monthly",1,IF(E16="Annual",12,60))) | H16: =G16*12 | I16: Priced in USD
A17: Health | B17: Dentist | C17: EUR | D17: 400 | E17: Annual | F17: 3 | G17: =IF(B17="",0,D17*IF(C17=Assumptions!$C$7,Assumptions!$C$5,1)/IF(E17="Monthly",1,IF(E17="Annual",12,60))) | H17: =G17*12
A18: Housing | B18: Home insurance | C18: EUR | D18: 350 | E18: Annual | F18: 1 | G18: =IF(B18="",0,D18*IF(C18=Assumptions!$C$7,Assumptions!$C$5,1)/IF(E18="Monthly",1,IF(E18="Annual",12,60))) | H18: =G18*12
A19: Travel | B19: Summer trip | C19: EUR | D19: 3000 | E19: Annual | F19: 7 | G19: =IF(B19="",0,D19*IF(C19=Assumptions!$C$7,Assumptions!$C$5,1)/IF(E19="Monthly",1,IF(E19="Annual",12,60))) | H19: =G19*12
A20: Household | B20: Replace appliances | C20: EUR | D20: 4000 | E20: 5-Year | G20: =IF(B20="",0,D20*IF(C20=Assumptions!$C$7,Assumptions!$C$5,1)/IF(E20="Monthly",1,IF(E20="Annual",12,60))) | H20: =G20*12 | I20: Smoothed at 1/60 a month
G21: =IF(B21="",0,D21*IF(C21=Assumptions!$C$7,Assumptions!$C$5,1)/IF(E21="Monthly",1,IF(E21="Annual",12,60))) | H21: =G21*12
G22: =IF(B22="",0,D22*IF(C22=Assumptions!$C$7,Assumptions!$C$5,1)/IF(E22="Monthly",1,IF(E22="Annual",12,60))) | H22: =G22*12
G23: =IF(B23="",0,D23*IF(C23=Assumptions!$C$7,Assumptions!$C$5,1)/IF(E23="Monthly",1,IF(E23="Annual",12,60))) | H23: =G23*12
G24: =IF(B24="",0,D24*IF(C24=Assumptions!$C$7,Assumptions!$C$5,1)/IF(E24="Monthly",1,IF(E24="Annual",12,60))) | H24: =G24*12
G25: =IF(B25="",0,D25*IF(C25=Assumptions!$C$7,Assumptions!$C$5,1)/IF(E25="Monthly",1,IF(E25="Annual",12,60))) | H25: =G25*12
G26: =IF(B26="",0,D26*IF(C26=Assumptions!$C$7,Assumptions!$C$5,1)/IF(E26="Monthly",1,IF(E26="Annual",12,60))) | H26: =G26*12
G27: =IF(B27="",0,D27*IF(C27=Assumptions!$C$7,Assumptions!$C$5,1)/IF(E27="Monthly",1,IF(E27="Annual",12,60))) | H27: =G27*12
G28: =IF(B28="",0,D28*IF(C28=Assumptions!$C$7,Assumptions!$C$5,1)/IF(E28="Monthly",1,IF(E28="Annual",12,60))) | H28: =G28*12
G29: =IF(B29="",0,D29*IF(C29=Assumptions!$C$7,Assumptions!$C$5,1)/IF(E29="Monthly",1,IF(E29="Annual",12,60))) | H29: =G29*12
G30: =IF(B30="",0,D30*IF(C30=Assumptions!$C$7,Assumptions!$C$5,1)/IF(E30="Monthly",1,IF(E30="Annual",12,60))) | H30: =G30*12
G31: =IF(B31="",0,D31*IF(C31=Assumptions!$C$7,Assumptions!$C$5,1)/IF(E31="Monthly",1,IF(E31="Annual",12,60))) | H31: =G31*12
G32: =IF(B32="",0,D32*IF(C32=Assumptions!$C$7,Assumptions!$C$5,1)/IF(E32="Monthly",1,IF(E32="Annual",12,60))) | H32: =G32*12
... G60: =IF(B60="",0,D60*IF(C60=Assumptions!$C$7,Assumptions!$C$5,1)/IF(E60="Monthly",1,IF(E60="Annual",12,60))) | H60: =G60*12
A62: Monthly lines | G62: =SUMIFS(G5:G60,E5:E60,"Monthly")
A63: Set-aside for annual and five-year lines | G63: =SUM(G5:G60)-G62
